aspubsub/__init__.py
aspubsub/aspubsub.py
aspubsub/lib.py
aspubsub/backends/__init__.py
aspubsub/backends/lib.py
aspubsub/backends/memory.py
aspubsub/backends/redis.py
aspubsub-0.1.3.dist-info/WHEEL
aspubsub-0.1.3.dist-info/METADATA
aspubsub-0.1.3.dist-info/RECORD
